[
  { "colors": [[0, 50, 255], [0, 0, 0], [0, 0, 0]], "duration": 0.1 },
  { "colors": [[0, 100, 255], [0, 50, 255], [0, 0, 0]], "duration": 0.1 },
  { "colors": [[0, 200, 255], [0, 100, 255], [0, 50, 255]], "duration": 0.1 },
  { "colors": [[255, 255, 0], [0, 200, 255], [0, 100, 255]], "duration": 0.1 },
  { "colors": [[0, 200, 255], [255, 255, 0], [0, 200, 255]], "duration": 0.1 },
  { "colors": [[0, 100, 255], [0, 200, 255], [255, 255, 0]], "duration": 0.1 },
  { "colors": [[0, 50, 255], [0, 100, 255], [0, 200, 255]], "duration": 0.1 },
  { "colors": [[0, 0, 0], [0, 50, 255], [0, 100, 255]], "duration": 0.1 },
  { "colors": [[0, 0, 0], [0, 0, 0], [0, 50, 255]], "duration": 0.1 },
  { "colors": [[0, 0, 0], [0, 0, 0], [0, 0, 0]], "duration": 0.1 },
  { "colors": [[0, 50, 255], [0, 0, 0], [0, 0, 0]], "duration": 0.1 },
  { "colors": [[0, 100, 255], [0, 50, 255], [0, 0, 0]], "duration": 0.1 },
  { "colors": [[0, 200, 255], [0, 100, 255], [0, 50, 255]], "duration": 0.1 },
  { "colors": [[255, 255, 0], [0, 200, 255], [0, 100, 255]], "duration": 0.1 },
  { "colors": [[0, 200, 255], [255, 255, 0], [0, 200, 255]], "duration": 0.1 },
  { "colors": [[0, 100, 255], [0, 200, 255], [255, 255, 0]], "duration": 0.1 },
  { "colors": [[0, 50, 255], [0, 100, 255], [0, 200, 255]], "duration": 0.1 },
  { "colors": [[0, 0, 0], [0, 50, 255], [0, 100, 255]], "duration": 0.1 },
  { "colors": [[0, 0, 0], [0, 0, 0], [0, 50, 255]], "duration": 0.1 },
  { "colors": [[0, 0, 0], [0, 0, 0], [0, 0, 0]], "duration": 0.1 },
  { "colors": [[0, 50, 255], [0, 50, 255], [0, 50, 255]], "duration": 0.1 },
  { "colors": [[0, 150, 255], [0, 150, 255], [0, 150, 255]], "duration": 0.1 },
  { "colors": [[255, 255, 100], [255, 255, 100], [255, 255, 100]], "duration": 0.1 },
  { "colors": [[0, 150, 255], [0, 150, 255], [0, 150, 255]], "duration": 0.1 },
  { "colors": [[0, 50, 255], [0, 50, 255], [0, 50, 255]], "duration": 0.1 },
  { "colors": [[0, 0, 0], [0, 0, 0], [0, 0, 0]], "duration": 0.1 },
  { "colors": [[0, 50, 255], [0, 50, 255], [0, 50, 255]], "duration": 0.1 },
  { "colors": [[0, 150, 255], [0, 150, 255], [0, 150, 255]], "duration": 0.1 },
  { "colors": [[255, 255, 100], [255, 255, 100], [255, 255, 100]], "duration": 0.1 },
  { "colors": [[0, 0, 0], [0, 0, 0], [0, 0, 0]], "duration": 0 }
]
